xbrl_filings_api/__about__.py
xbrl_filings_api/__init__.py
xbrl_filings_api/__main__.py
xbrl_filings_api/api_error.py
xbrl_filings_api/api_object.py
xbrl_filings_api/api_page.py
xbrl_filings_api/api_request.py
xbrl_filings_api/api_resource.py
xbrl_filings_api/constants.py
xbrl_filings_api/database_processor.py
xbrl_filings_api/debug.py
xbrl_filings_api/default_views.py
xbrl_filings_api/download_info.py
xbrl_filings_api/download_item.py
xbrl_filings_api/download_specs_construct.py
xbrl_filings_api/entity.py
xbrl_filings_api/exceptions.py
xbrl_filings_api/filing.py
xbrl_filings_api/filing_set.py
xbrl_filings_api/filings_page.py
xbrl_filings_api/json_tree.py
xbrl_filings_api/lang_code_transform.py
xbrl_filings_api/options.py
xbrl_filings_api/order_columns.py
xbrl_filings_api/parse_type.py
xbrl_filings_api/query.py
xbrl_filings_api/request_processor.py
xbrl_filings_api/resource_collection.py
xbrl_filings_api/scope_flag.py
xbrl_filings_api/sqlite_view.py
xbrl_filings_api/stats.py
xbrl_filings_api/validation_message.py
xbrl_filings_api/downloader/__init__.py
xbrl_filings_api/downloader/download_processor.py
xbrl_filings_api/downloader/download_result.py
xbrl_filings_api/downloader/download_specs.py
xbrl_filings_api/downloader/exceptions.py
xbrl_filings_api/downloader/stats.py
xbrl_filings_api-1.0.dist-info/METADATA
xbrl_filings_api-1.0.dist-info/WHEEL
xbrl_filings_api-1.0.dist-info/licenses/LICENSE.txt
xbrl_filings_api-1.0.dist-info/RECORD
